{
    "libros": [
      {
        "titulo": "Cien años de soledad",
        "autor": "Gabriel García Márquez",
        "anio_publicacion": 1967,
        "genero": "Realismo mágico",
        "editorial": "Sudamericana",
        "disponible": true
      },
      {
        "titulo": "1984",
        "autor": "George Orwell",
        "anio_publicacion": 1949,
        "genero": "Distopía",
        "editorial": "Secker & Warburg",
        "disponible": true
      },
      {
        "titulo": "Matar a un ruiseñor",
        "autor": "Harper Lee",
        "anio_publicacion": 1960,
        "genero": "Novela",
        "editorial": "J.B. Lippincott & Co.",
        "disponible": false
      },
      {
        "titulo": "Orgullo y prejuicio",
        "autor": "Jane Austen",
        "anio_publicacion": 1813,
        "genero": "Novela romántica",
        "editorial": "T. Egerton, Whitehall",
        "disponible": true
      },
      {
        "titulo": "El señor de los anillos",
        "autor": "J.R.R. Tolkien",
        "anio_publicacion": 1954,
        "genero": "Fantasía",
        "editorial": "Allen & Unwin",
        "disponible": true
      },
      {
        "titulo": "Crónica de una muerte anunciada",
        "autor": "Gabriel García Márquez",
        "anio_publicacion": 1981,
        "genero": "Novela",
        "editorial": "Sudamericana",
        "disponible": true
      },
      {
        "titulo": "Mujer en punto cero",
        "autor": "Nawal El Saadawi",
        "anio_publicacion": 1975,
        "genero": "Feminismo",
        "editorial": "Dar al-Mustaqbal",
        "disponible": false
      },
      {
        "titulo": "Crimen y castigo",
        "autor": "Fyodor Dostoevsky",
        "anio_publicacion": 1866,
        "genero": "Novela psicológica",
        "editorial": "The Russian Messenger",
        "disponible": true
      },
      {
        "titulo": "Los hombres que no amaban a las mujeres",
        "autor": "Stieg Larsson",
        "anio_publicacion": 2005,
        "genero": "Thriller",
        "editorial": "Norstedts Förlag",
        "disponible": true
      },
      {
        "titulo": "El Gran Gatsby",
        "autor": "F. Scott Fitzgerald",
        "anio_publicacion": 1925,
        "genero": "Novela",
        "editorial": "Charles Scribner's Sons",
        "disponible": true
      }
    ]
  }
  